etc/vmm_workload_auto/conf.yml
etc/vmm_workload_auto/conf_multiple_dcnm.yml
etc/vmm_workload_auto/conf_multiple_vcenter.yml
etc/vmm_workload_auto/sample.csv
vmm_workload_auto-1.0.5.data/scripts/setup.sh
vmm_workload_auto-1.0.5.dist-info/DESCRIPTION.rst
vmm_workload_auto-1.0.5.dist-info/METADATA
vmm_workload_auto-1.0.5.dist-info/RECORD
vmm_workload_auto-1.0.5.dist-info/WHEEL
vmm_workload_auto-1.0.5.dist-info/entry_points.txt
vmm_workload_auto-1.0.5.dist-info/metadata.json
vmm_workload_auto-1.0.5.dist-info/top_level.txt
workload_auto/__init__.py
workload_auto/dcnm_helper.py
workload_auto/dcnm_top.py
workload_auto/logger.py
workload_auto/main.py
workload_auto/rest.py
workload_auto/utils.py
workload_auto/vsph_handler.py
workload_auto/vsphere_helper.py
