Metadata-Version: 2.0
Name: vmm-workload-auto
Version: 1.0.5
Summary: Workload Automation for VMM
Home-page: https://www.cisco.com
Author: Padmanabhan Krishnan
Author-email: padkrish@cisco.com
License: UNKNOWN
Platform: UNKNOWN
Requires-Dist: Flask
Requires-Dist: PyYAML (==5.3)
Requires-Dist: pyvim (==3.0.2)
Requires-Dist: pyvmomi (==7.0)
